Metadata-Version: 1.1
Name: dtool-annotation
Version: 0.1.1
Summary: Add ability to annotate datasets using the dtool CLI
Home-page: https://github.com/jic-dtool/dtool-annotation
Author: Tjelvar Olsson
Author-email: tjelvar.olsson@gmail.com
License: MIT
Download-URL: https://github.com/jic-dtool/dtool-annotation/tarball/0.1.1
Platform: UNKNOWN
